{
  "version": "6",
  "dialect": "sqlite",
  "id": "2e02224e-f565-48e4-955d-536d3259aa2e",
  "prevId": "a238c107-65fa-451e-bc84-6b9506dcaac6",
  "tables": {
    "artists": {
      "name": "artists",
      "columns": {
        "artist_id": {
          "name": "artist_id",
          "type": "integer",
          "primaryKey": true,
          "notNull": true,
          "autoincrement": false
        },
        "name": {
          "name": "name",
          "type": "text",
          "primaryKey": false,
          "notNull": true,
          "autoincrement": false
        }
      },
      "indexes": {},
      "foreignKeys": {},
      "compositePrimaryKeys": {},
      "uniqueConstraints": {}
    },
    "playlist_songs": {
      "name": "playlist_songs",
      "columns": {
        "playlist_song_id": {
          "name": "playlist_song_id",
          "type": "integer",
          "primaryKey": true,
          "notNull": true,
          "autoincrement": false
        },
        "playlist_id": {
          "name": "playlist_id",
          "type": "integer",
          "primaryKey": false,
          "notNull": true,
          "autoincrement": false
        },
        "song_id": {
          "name": "song_id",
          "type": "integer",
          "primaryKey": false,
          "notNull": true,
          "autoincrement": false
        }
      },
      "indexes": {},
      "foreignKeys": {
        "playlist_songs_playlist_id_playlists_playlist_id_fk": {
          "name": "playlist_songs_playlist_id_playlists_playlist_id_fk",
          "tableFrom": "playlist_songs",
          "tableTo": "playlists",
          "columnsFrom": [
            "playlist_id"
          ],
          "columnsTo": [
            "playlist_id"
          ],
          "onDelete": "no action",
          "onUpdate": "no action"
        },
        "playlist_songs_song_id_songs_song_id_fk": {
          "name": "playlist_songs_song_id_songs_song_id_fk",
          "tableFrom": "playlist_songs",
          "tableTo": "songs",
          "columnsFrom": [
            "song_id"
          ],
          "columnsTo": [
            "song_id"
          ],
          "onDelete": "no action",
          "onUpdate": "no action"
        }
      },
      "compositePrimaryKeys": {},
      "uniqueConstraints": {}
    },
    "playlists": {
      "name": "playlists",
      "columns": {
        "playlist_id": {
          "name": "playlist_id",
          "type": "integer",
          "primaryKey": true,
          "notNull": true,
          "autoincrement": false
        },
        "user_id": {
          "name": "user_id",
          "type": "integer",
          "primaryKey": false,
          "notNull": true,
          "autoincrement": false
        },
        "name": {
          "name": "name",
          "type": "text",
          "primaryKey": false,
          "notNull": true,
          "autoincrement": false
        },
        "current_song_id": {
          "name": "current_song_id",
          "type": "integer",
          "primaryKey": false,
          "notNull": true,
          "autoincrement": false
        },
        "percent_until_replayable": {
          "name": "percent_until_replayable",
          "type": "real",
          "primaryKey": false,
          "notNull": true,
          "autoincrement": false
        },
        "version": {
          "name": "version",
          "type": "integer",
          "primaryKey": false,
          "notNull": true,
          "autoincrement": false
        }
      },
      "indexes": {},
      "foreignKeys": {
        "playlists_user_id_users_user_id_fk": {
          "name": "playlists_user_id_users_user_id_fk",
          "tableFrom": "playlists",
          "tableTo": "users",
          "columnsFrom": [
            "user_id"
          ],
          "columnsTo": [
            "user_id"
          ],
          "onDelete": "no action",
          "onUpdate": "no action"
        }
      },
      "compositePrimaryKeys": {},
      "uniqueConstraints": {}
    },
    "song_artists": {
      "name": "song_artists",
      "columns": {
        "song_artist_id": {
          "name": "song_artist_id",
          "type": "integer",
          "primaryKey": true,
          "notNull": true,
          "autoincrement": false
        },
        "song_id": {
          "name": "song_id",
          "type": "integer",
          "primaryKey": false,
          "notNull": true,
          "autoincrement": false
        },
        "artist_id": {
          "name": "artist_id",
          "type": "integer",
          "primaryKey": false,
          "notNull": true,
          "autoincrement": false
        }
      },
      "indexes": {},
      "foreignKeys": {
        "song_artists_song_id_songs_song_id_fk": {
          "name": "song_artists_song_id_songs_song_id_fk",
          "tableFrom": "song_artists",
          "tableTo": "songs",
          "columnsFrom": [
            "song_id"
          ],
          "columnsTo": [
            "song_id"
          ],
          "onDelete": "no action",
          "onUpdate": "no action"
        },
        "song_artists_artist_id_artists_artist_id_fk": {
          "name": "song_artists_artist_id_artists_artist_id_fk",
          "tableFrom": "song_artists",
          "tableTo": "artists",
          "columnsFrom": [
            "artist_id"
          ],
          "columnsTo": [
            "artist_id"
          ],
          "onDelete": "no action",
          "onUpdate": "no action"
        }
      },
      "compositePrimaryKeys": {},
      "uniqueConstraints": {}
    },
    "songs": {
      "name": "songs",
      "columns": {
        "song_id": {
          "name": "song_id",
          "type": "integer",
          "primaryKey": true,
          "notNull": true,
          "autoincrement": false
        },
        "directory": {
          "name": "directory",
          "type": "text",
          "primaryKey": false,
          "notNull": true,
          "autoincrement": false
        },
        "name": {
          "name": "name",
          "type": "text",
          "primaryKey": false,
          "notNull": true,
          "autoincrement": false
        }
      },
      "indexes": {
        "idx_songs_name": {
          "name": "idx_songs_name",
          "columns": [
            "name"
          ],
          "isUnique": false
        }
      },
      "foreignKeys": {},
      "compositePrimaryKeys": {},
      "uniqueConstraints": {}
    },
    "song_tags": {
      "name": "song_tags",
      "columns": {
        "song_tag_id": {
          "name": "song_tag_id",
          "type": "integer",
          "primaryKey": true,
          "notNull": true,
          "autoincrement": false
        },
        "song_id": {
          "name": "song_id",
          "type": "integer",
          "primaryKey": false,
          "notNull": true,
          "autoincrement": false
        },
        "tag_id": {
          "name": "tag_id",
          "type": "integer",
          "primaryKey": false,
          "notNull": true,
          "autoincrement": false
        }
      },
      "indexes": {},
      "foreignKeys": {
        "song_tags_song_id_songs_song_id_fk": {
          "name": "song_tags_song_id_songs_song_id_fk",
          "tableFrom": "song_tags",
          "tableTo": "songs",
          "columnsFrom": [
            "song_id"
          ],
          "columnsTo": [
            "song_id"
          ],
          "onDelete": "no action",
          "onUpdate": "no action"
        },
        "song_tags_tag_id_tags_tag_id_fk": {
          "name": "song_tags_tag_id_tags_tag_id_fk",
          "tableFrom": "song_tags",
          "tableTo": "tags",
          "columnsFrom": [
            "tag_id"
          ],
          "columnsTo": [
            "tag_id"
          ],
          "onDelete": "no action",
          "onUpdate": "no action"
        }
      },
      "compositePrimaryKeys": {},
      "uniqueConstraints": {}
    },
    "tags": {
      "name": "tags",
      "columns": {
        "tag_id": {
          "name": "tag_id",
          "type": "integer",
          "primaryKey": true,
          "notNull": true,
          "autoincrement": false
        },
        "name": {
          "name": "name",
          "type": "text",
          "primaryKey": false,
          "notNull": true,
          "autoincrement": false
        }
      },
      "indexes": {},
      "foreignKeys": {},
      "compositePrimaryKeys": {},
      "uniqueConstraints": {}
    },
    "users": {
      "name": "users",
      "columns": {
        "user_id": {
          "name": "user_id",
          "type": "integer",
          "primaryKey": true,
          "notNull": true,
          "autoincrement": false
        },
        "username": {
          "name": "username",
          "type": "text",
          "primaryKey": false,
          "notNull": true,
          "autoincrement": false
        },
        "version": {
          "name": "version",
          "type": "integer",
          "primaryKey": false,
          "notNull": true,
          "autoincrement": false
        }
      },
      "indexes": {},
      "foreignKeys": {},
      "compositePrimaryKeys": {},
      "uniqueConstraints": {}
    }
  },
  "enums": {},
  "_meta": {
    "schemas": {},
    "tables": {},
    "columns": {}
  },
  "internal": {
    "indexes": {}
  }
}